linkedin_analytics_to_sqlite/__init__.py
linkedin_analytics_to_sqlite/cli.py
linkedin_analytics_to_sqlite-0.0.2.dist-info/LICENSE
linkedin_analytics_to_sqlite-0.0.2.dist-info/METADATA
linkedin_analytics_to_sqlite-0.0.2.dist-info/WHEEL
linkedin_analytics_to_sqlite-0.0.2.dist-info/entry_points.txt
linkedin_analytics_to_sqlite-0.0.2.dist-info/RECORD
